{"expireTime":9007200819241831000,"key":"create-remote-file-node-https://scontent-arn2-1.cdninstagram.com/vp/237a5120bfdbb097b12b83dbfe7c4b12/5D434D0F/t51.2885-15/e35/65135576_207509420146659_8509660682918681103_n.jpg?_nc_ht=scontent-arn2-1.cdninstagram.com","val":{"last-modified":"Sun, 07 Jul 2019 07:29:31 GMT","x-haystack-needlechecksum":"1457150934","x-needle-checksum":"2001342361","content-type":"image/jpeg","x-fb-config-version-olb-prod":"522","timing-allow-origin":"*","access-control-allow-origin":"*","cache-control":"max-age=1209600, no-transform","x-enc-origin-req-handler":"AcLj0epoiB5ifcQC9yLpzrhOrLYH7nvX-i3iXpyV7o6SvH7M14_rn2FtEXDRRHtBZHDyV_c-7gdgLjZRpA","x-fb-trip-id":"1679558926","date":"Tue, 30 Jul 2019 15:34:00 GMT","connection":"close","content-length":"100160"}}